Metadata-Version: 2.1
Name: gtsam
Version: 4.1.1
Summary: Georgia Tech Smoothing And Mapping library
Home-page: https://gtsam.org/
Author: Frank Dellaert et. al.
Author-email: frank.dellaert@gtsam.org
License: Simplified BSD license
Keywords: slam sam robotics localization mapping optimization
Platform: UNKNOWN
Classifier: Development Status :: 5 - Production/Stable
Classifier: Intended Audience :: Education
Classifier: Intended Audience :: Developers
Classifier: Intended Audience :: Science/Research
Classifier: Operating System :: MacOS
Classifier: Operating System :: Microsoft :: Windows
Classifier: Operating System :: POSIX
Classifier: License :: OSI Approved :: BSD License
Classifier: Programming Language :: Python :: 2
Classifier: Programming Language :: Python :: 3
Requires-Dist: numpy (>=1.11.0)
Requires-Dist: pyparsing (>=2.4.2)
